<?xml version="1.0" encoding="UTF-8"?>
<?xml-stylesheet type="text/xsl" href="specifikace_vozidla.xsl"?>
<specifikace_vozidla> <!-- xmlns:xsi="http://www.w3.org/2001/XMLSchema-instance" xsi:noNamespaceSchemaLocation="specifikace_vozidla.xsd">-->
<vozidlo>
    <Vyrobce>Skoda</Vyrobce>
    <Typ>
        <jmeno>Octavia</jmeno>
        <typ_karoserie>Sedan</typ_karoserie>
        <material_karoserie>Hlinik</material_karoserie>
        <vyska_vozidla jednotky="mm">1461</vyska_vozidla>
        <sirka_vozidla jednotky="mm">2017</sirka_vozidla>
        <delka_vozidla jednotky="mm">4659</delka_vozidla>
        <rozvor_naprav jednotky="mm">2686</rozvor_naprav>
        <objem_kufru jednotky="l">590/1580</objem_kufru>
        <hmotnost jednotky="kg">1342</hmotnost>
        <barva>Modra</barva>
        <typ_barvy oznaceni_barvy="race">Metaliza</typ_barvy>
    </Typ>
       
    <Pohonne_hmoty>
        <palivo doporucene="oktanove cislo min. 95">Benzin</palivo>
        <spotreba jednotky="l/100km">5,9</spotreba>
        <objem_nadrze jednotky="l">50</objem_nadrze>
    </Pohonne_hmoty>
    
    <Motor>
        <druh>Zazehovy</druh>
        <oznaceni>TSI</oznaceni>
        <objem jednotky="cm^3">1798</objem>
        <pocet__valcu>4</pocet__valcu>
        <max_vykon jednotky="kW">132</max_vykon>
        <max_otacky>5100-6200</max_otacky>
        <max_tocivy_moment jednotky="nM">250</max_tocivy_moment>
        <exhalacni_norma>EU6</exhalacni_norma>
        <emise jednotky="g/km">136</emise>
        <max_rychlost jednotky="km/h">229</max_rychlost>
        <zrychleni rozmezi="0-100km/h">7,3</zrychleni>
        <pocet_stupnu typ_prevodovky="manualni">6</pocet_stupnu>
        <spojka typ_ovladani="hydraulicke">Jednokotoucova</spojka>
        <nahon pocet_pohanenych_kol="2">Predni kola</nahon>        
    </Motor>
    
    <Vybava>
        <typ_vybavy>Style</typ_vybavy>
        <barva_interieru>Cerna</barva_interieru>
        <signalizace_pri_parkovani>Ano</signalizace_pri_parkovani>
        <klimatizace vyrobce="Climatronic">Dvouzonova</klimatizace>
        <tempomat>Ano</tempomat>
        <vyhrivani_sedadel>Predni</vyhrivani_sedadel>
        <typ_svetlometu>LED</typ_svetlometu>
        <autoradio>Ano</autoradio>
        <palubni_pocitac>Ano</palubni_pocitac>
        <abs>Ano</abs>
        <asr>Ano</asr>
        <esp>Ano</esp>
        <tazne_zarizeni nadstandard="ano">Ano</tazne_zarizeni>
        <mlhovky nadstandard="ano">Ano</mlhovky>
        <lane_assist nadstandard="ano">Ano</lane_assist>
    </Vybava>
    
    <Brzdy>
        <typ_brzd>Kotoucove</typ_brzd>
    </Brzdy>
    
    <Kola>
        <standardni_kola rozmer="16">Ne</standardni_kola>
        <nadstandardni_kola rozmer="18">Ano</nadstandardni_kola>
        <material>Lehka slitina</material>
    </Kola>
    
    <Cenik>
        <celkova_cena mena="Kc">752300</celkova_cena>
        <cena_nadstandardni_vybavy mena="Kc">29900</cena_nadstandardni_vybavy>
        <cena_metalicke_barvy mena="Kc">14700</cena_metalicke_barvy>
        <cena_kol>12800</cena_kol>
        <na_splatky>Ano</na_splatky>
    </Cenik>
    
    <Dodatecne_informace>
        <ujeto jednotky="km">30124</ujeto>
        <rok_vyroby>2016</rok_vyroby>
        <bourano>Ne</bourano>
        <osobni_vlastnictvi>Ne</osobni_vlastnictvi>
    </Dodatecne_informace>
    
</vozidlo>
</specifikace_vozidla>    
